{
  "version": "1.0",
  "cards": [
    {
      "number": 1,
      "name": "愚者",
      "type": "大阿卡纳",
      "suit": null,
      "upright": "新的开始、冒险、纯真、无限可能",
      "reversed": "鲁莽、愚蠢、不顾后果、不成熟"
    },
    {
      "number": 2,
      "name": "魔术师",
      "type": "大阿卡纳",
      "suit": null,
      "upright": "创造力、技能、意志力、资源整合",
      "reversed": "欺骗、浪费天赋、操纵、未发挥潜力"
    },
    {
      "number": 3,
      "name": "女祭司",
      "type": "大阿卡纳",
      "suit": null,
      "upright": "直觉、神秘、内在智慧、潜意识",
      "reversed": "表面化、忽视直觉、隐藏的秘密"
    },
    {
      "number": 4,
      "name": "女皇",
      "type": "大阿卡纳",
      "suit": null,
      "upright": "丰饶、母性、创造力、自然之美",
      "reversed": "依赖、空虚、创作力受阻"
    },
    {
      "number": 5,
      "name": "皇帝",
      "type": "大阿卡纳",
      "suit": null,
      "upright": "权威、稳定、父性、结构、秩序",
      "reversed": "专制、僵化、滥用权力"
    },
    {
      "number": 6,
      "name": "教皇",
      "type": "大阿卡纳",
      "suit": null,
      "upright": "传统、精神指导、信仰、教诲",
      "reversed": "叛逆、打破规则、过度保守"
    },
    {
      "number": 7,
      "name": "恋人",
      "type": "大阿卡纳",
      "suit": null,
      "upright": "爱情、选择、和谐、合一",
      "reversed": "失衡、价值观冲突、分离"
    },
    {
      "number": 8,
      "name": "战车",
      "type": "大阿卡纳",
      "suit": null,
      "upright": "胜利、意志力、控制、决心",
      "reversed": "失控、侵略、方向迷失"
    },
    {
      "number": 9,
      "name": "力量",
      "type": "大阿卡纳",
      "suit": null,
      "upright": "勇气、耐心、内在力量、温和控制",
      "reversed": "软弱、自我怀疑、缺乏自信"
    },
    {
      "number": 10,
      "name": "隐士",
      "type": "大阿卡纳",
      "suit": null,
      "upright": "内省、寻找真相、智慧、指引",
      "reversed": "孤独、退缩、迷失方向"
    },
    {
      "number": 11,
      "name": "命运之轮",
      "type": "大阿卡纳",
      "suit": null,
      "upright": "命运、转变、好运、循环",
      "reversed": "坏运、厄运循环、抗拒改变"
    },
    {
      "number": 12,
      "name": "正义",
      "type": "大阿卡纳",
      "suit": null,
      "upright": "公正、诚实、因果、平衡",
      "reversed": "不公、推卸责任、自欺欺人"
    },
    {
      "number": 13,
      "name": "倒吊人",
      "type": "大阿卡纳",
      "suit": null,
      "upright": "牺牲、等待、新视角、放下",
      "reversed": "拖延、抗拒、白白牺牲"
    },
    {
      "number": 14,
      "name": "死神",
      "type": "大阿卡纳",
      "suit": null,
      "upright": "结束、转变、重生、放下过去",
      "reversed": "抗拒改变、停滞、恐惧"
    },
    {
      "number": 15,
      "name": "节制",
      "type": "大阿卡纳",
      "suit": null,
      "upright": "平衡、耐心、调和、适度",
      "reversed": "极端、失衡、急躁"
    },
    {
      "number": 16,
      "name": "恶魔",
      "type": "大阿卡纳",
      "suit": null,
      "upright": "束缚、上瘾、物质主义、执念",
      "reversed": "觉醒、挣脱枷锁、重获自由"
    },
    {
      "number": 17,
      "name": "塔",
      "type": "大阿卡纳",
      "suit": null,
      "upright": "剧变、崩塌、觉醒、启示",
      "reversed": "灾难预警、拒绝改变"
    },
    {
      "number": 18,
      "name": "星星",
      "type": "大阿卡纳",
      "suit": null,
      "upright": "希望、灵感、平静、指引",
      "reversed": "绝望、失去方向、信心低落"
    },
    {
      "number": 19,
      "name": "月亮",
      "type": "大阿卡纳",
      "suit": null,
      "upright": "幻象、恐惧、潜意识、不确定性",
      "reversed": "解除恐惧、认清幻觉"
    },
    {
      "number": 20,
      "name": "太阳",
      "type": "大阿卡纳",
      "suit": null,
      "upright": "成功、喜悦、活力、成就",
      "reversed": "暂时的挫折、过于乐观"
    },
    {
      "number": 21,
      "name": "审判",
      "type": "大阿卡纳",
      "suit": null,
      "upright": "重生、觉醒、自我评估、宽恕",
      "reversed": "自我怀疑、拒绝自省"
    },
    {
      "number": 22,
      "name": "世界",
      "type": "大阿卡纳",
      "suit": null,
      "upright": "完成、圆满、旅程终点、成就",
      "reversed": "未完成、停滞、寻找归宿"
    }
  ],
  "cards_minor": [
    {
      "number": 23,
      "name": "权杖王牌",
      "type": "小阿卡纳",
      "suit": "权杖",
      "upright": "新开始、创造力、灵感",
      "reversed": "延迟、计划受阻"
    },
    {
      "number": 24,
      "name": "权杖二",
      "type": "小阿卡纳",
      "suit": "权杖",
      "upright": "规划、决策、未来方向",
      "reversed": "犹豫、恐惧未知"
    },
    {
      "number": 25,
      "name": "权杖三",
      "type": "小阿卡纳",
      "suit": "权杖",
      "upright": "远见、扩张、领导力",
      "reversed": "挫折、计划延迟"
    },
    {
      "number": 26,
      "name": "权杖四",
      "type": "小阿卡纳",
      "suit": "权杖",
      "upright": "庆祝、和谐、归属感",
      "reversed": "动荡、家不和"
    },
    {
      "number": 27,
      "name": "权杖五",
      "type": "小阿卡纳",
      "suit": "权杖",
      "upright": "竞争、冲突、挑战",
      "reversed": "妥协、避免冲突"
    },
    {
      "number": 28,
      "name": "权杖六",
      "type": "小阿卡纳",
      "suit": "权杖",
      "upright": "胜利、认可、好消息",
      "reversed": "骄傲、失败、不被认可"
    },
    {
      "number": 29,
      "name": "权杖七",
      "type": "小阿卡纳",
      "suit": "权杖",
      "upright": "坚持、防御、挑战",
      "reversed": "放弃、不堪重负"
    },
    {
      "number": 30,
      "name": "权杖八",
      "type": "小阿卡纳",
      "suit": "权杖",
      "upright": "快速行动、进展、消息",
      "reversed": "延误、慢下来"
    },
    {
      "number": 31,
      "name": "权杖九",
      "type": "小阿卡纳",
      "suit": "权杖",
      "upright": "毅力、警觉、坚持到底",
      "reversed": "偏执、疲惫、放弃"
    },
    {
      "number": 32,
      "name": "权杖十",
      "type": "小阿卡纳",
      "suit": "权杖",
      "upright": "负担、压力、过度付出",
      "reversed": "卸下重担、放手"
    },
    {
      "number": 33,
      "name": "权杖侍者",
      "type": "小阿卡纳",
      "suit": "权杖",
      "upright": "热情、探索、信使",
      "reversed": "缺乏方向、冲动"
    },
    {
      "number": 34,
      "name": "权杖骑士",
      "type": "小阿卡纳",
      "suit": "权杖",
      "upright": "行动、冒险、充满活力",
      "reversed": "鲁莽、急躁、冲动"
    },
    {
      "number": 35,
      "name": "权杖王后",
      "type": "小阿卡纳",
      "suit": "权杖",
      "upright": "自信、魅力、温暖",
      "reversed": "嫉妒、苛刻、压抑"
    },
    {
      "number": 36,
      "name": "权杖国王",
      "type": "小阿卡纳",
      "suit": "权杖",
      "upright": "领导力、远见、企业家精神",
      "reversed": "专制、苛刻、严苛"
    },
    {
      "number": 37,
      "name": "圣杯王牌",
      "type": "小阿卡纳",
      "suit": "圣杯",
      "upright": "新感情、爱、直觉",
      "reversed": "感情空虚、关闭心扉"
    },
    {
      "number": 38,
      "name": "圣杯二",
      "type": "小阿卡纳",
      "suit": "圣杯",
      "upright": "结合、合作伙伴、吸引力",
      "reversed": "分手、不平衡的关系"
    },
    {
      "number": 39,
      "name": "圣杯三",
      "type": "小阿卡纳",
      "suit": "圣杯",
      "upright": "庆祝、友谊、社群",
      "reversed": "过度享乐、流言蜚语"
    },
    {
      "number": 40,
      "name": "圣杯四",
      "type": "小阿卡纳",
      "suit": "圣杯",
      "upright": "沉思、不满、自省",
      "reversed": "新的机会、觉醒"
    },
    {
      "number": 41,
      "name": "圣杯五",
      "type": "小阿卡纳",
      "suit": "圣杯",
      "upright": "失落、悲伤、失望",
      "reversed": "接受、向前看"
    },
    {
      "number": 42,
      "name": "圣杯六",
      "type": "小阿卡纳",
      "suit": "圣杯",
      "upright": "怀旧、回忆、童年、安全感",
      "reversed": "活在过去、停滞不前"
    },
    {
      "number": 43,
      "name": "圣杯七",
      "type": "小阿卡纳",
      "suit": "圣杯",
      "upright": "幻想、选择、白日梦",
      "reversed": "明确目标、聚焦"
    },
    {
      "number": 44,
      "name": "圣杯八",
      "type": "小阿卡纳",
      "suit": "圣杯",
      "upright": "放手、追寻、离开舒适区",
      "reversed": "害怕改变、继续停滞"
    },
    {
      "number": 45,
      "name": "圣杯九",
      "type": "小阿卡纳",
      "suit": "圣杯",
      "upright": "满足、愿望成真、享受",
      "reversed": "不满足、缺乏内在满足"
    },
    {
      "number": 46,
      "name": "圣杯十",
      "type": "小阿卡纳",
      "suit": "圣杯",
      "upright": "幸福、和谐、家庭之爱",
      "reversed": "家庭矛盾、破碎"
    },
    {
      "number": 47,
      "name": "圣杯侍者",
      "type": "小阿卡纳",
      "suit": "圣杯",
      "upright": "创意、直觉、新消息",
      "reversed": "情感不成熟、逃避"
    },
    {
      "number": 48,
      "name": "圣杯骑士",
      "type": "小阿卡纳",
      "suit": "圣杯",
      "upright": "浪漫、幻想、追求",
      "reversed": "情绪化、嫉妒、控制"
    },
    {
      "number": 49,
      "name": "圣杯王后",
      "type": "小阿卡纳",
      "suit": "圣杯",
      "upright": "温柔、直觉、关怀、情感丰富",
      "reversed": "情感依赖、容易受伤"
    },
    {
      "number": 50,
      "name": "圣杯国王",
      "type": "小阿卡纳",
      "suit": "圣杯",
      "upright": "情绪成熟、慈悲、智慧",
      "reversed": "情绪压抑、冷酷"
    },
    {
      "number": 51,
      "name": "宝剑王牌",
      "type": "小阿卡纳",
      "suit": "宝剑",
      "upright": "清晰、真理、突破",
      "reversed": "困惑、误解、谎言"
    },
    {
      "number": 52,
      "name": "宝剑二",
      "type": "小阿卡纳",
      "suit": "宝剑",
      "upright": "僵局、逃避、艰难选择",
      "reversed": "面对现实、做出决定"
    },
    {
      "number": 53,
      "name": "宝剑三",
      "type": "小阿卡纳",
      "suit": "宝剑",
      "upright": "心碎、悲伤、痛苦",
      "reversed": "疗愈、释放痛苦"
    },
    {
      "number": 54,
      "name": "宝剑四",
      "type": "小阿卡纳",
      "suit": "宝剑",
      "upright": "休息、放松、沉思",
      "reversed": "焦虑、恢复活动"
    },
    {
      "number": 55,
      "name": "宝剑五",
      "type": "小阿卡纳",
      "suit": "宝剑",
      "upright": "冲突、败局、损失",
      "reversed": "和解、放下过去"
    },
    {
      "number": 56,
      "name": "宝剑六",
      "type": "小阿卡纳",
      "suit": "宝剑",
      "upright": "过渡、前行、疗愈之路",
      "reversed": "卡住、不愿前行"
    },
    {
      "number": 57,
      "name": "宝剑七",
      "type": "小阿卡纳",
      "suit": "宝剑",
      "upright": "策略、欺骗、隐藏",
      "reversed": "诚实、真相大白"
    },
    {
      "number": 58,
      "name": "宝剑八",
      "type": "小阿卡纳",
      "suit": "宝剑",
      "upright": "束缚、自我限制、无助",
      "reversed": "觉醒、解放、突破"
    },
    {
      "number": 59,
      "name": "宝剑九",
      "type": "小阿卡纳",
      "suit": "宝剑",
      "upright": "焦虑、噩梦、极度担忧",
      "reversed": "疗愈、面对恐惧"
    },
    {
      "number": 60,
      "name": "宝剑十",
      "type": "小阿卡纳",
      "suit": "宝剑",
      "upright": "终结、背叛、谷底",
      "reversed": "重生、雨后彩虹"
    },
    {
      "number": 61,
      "name": "宝剑侍者",
      "type": "小阿卡纳",
      "suit": "宝剑",
      "upright": "好奇、警觉、思维活跃",
      "reversed": "多疑、尖刻、冲动"
    },
    {
      "number": 62,
      "name": "宝剑骑士",
      "type": "小阿卡纳",
      "suit": "宝剑",
      "upright": "行动、野心、决断",
      "reversed": "冒进、冲动、缺乏耐性"
    },
    {
      "number": 63,
      "name": "宝剑王后",
      "type": "小阿卡纳",
      "suit": "宝剑",
      "upright": "独立、理性、果决",
      "reversed": "冷酷、严厉、刻薄"
    },
    {
      "number": 64,
      "name": "宝剑国王",
      "type": "小阿卡纳",
      "suit": "宝剑",
      "upright": "理性、权威、公平",
      "reversed": "专制、滥用权力"
    },
    {
      "number": 65,
      "name": "钱币王牌",
      "type": "小阿卡纳",
      "suit": "钱币",
      "upright": "新机会、繁荣、开始",
      "reversed": "错失机会、财务损失"
    },
    {
      "number": 66,
      "name": "钱币二",
      "type": "小阿卡纳",
      "suit": "钱币",
      "upright": "平衡、适应、资源分配",
      "reversed": "不平衡、财务混乱"
    },
    {
      "number": 67,
      "name": "钱币三",
      "type": "小阿卡纳",
      "suit": "钱币",
      "upright": "团队合作、技能、学习",
      "reversed": "缺乏合作、水准差"
    },
    {
      "number": 68,
      "name": "钱币四",
      "type": "小阿卡纳",
      "suit": "钱币",
      "upright": "稳定、节俭、占有",
      "reversed": "贪婪、守财、恐惧失去"
    },
    {
      "number": 69,
      "name": "钱币五",
      "type": "小阿卡纳",
      "suit": "钱币",
      "upright": "贫困、孤立、逆境",
      "reversed": "经济好转、走出困境"
    },
    {
      "number": 70,
      "name": "钱币六",
      "type": "小阿卡纳",
      "suit": "钱币",
      "upright": "分享、慈善、给予",
      "reversed": "自私、不平等"
    },
    {
      "number": 71,
      "name": "钱币七",
      "type": "小阿卡纳",
      "suit": "钱币",
      "upright": "耐心、投资、评估",
      "reversed": "浪费、短视"
    },
    {
      "number": 72,
      "name": "钱币八",
      "type": "小阿卡纳",
      "suit": "钱币",
      "upright": "努力、技能、勤劳",
      "reversed": "敷衍、缺乏热情"
    },
    {
      "number": 73,
      "name": "钱币九",
      "type": "小阿卡纳",
      "suit": "钱币",
      "upright": "富足、自给自足、享受",
      "reversed": "物质依赖、不满足"
    },
    {
      "number": 74,
      "name": "钱币十",
      "type": "小阿卡纳",
      "suit": "钱币",
      "upright": "财富、传承、事业成功",
      "reversed": "财务损失、遗产纠纷"
    },
    {
      "number": 75,
      "name": "钱币侍者",
      "type": "小阿卡纳",
      "suit": "钱币",
      "upright": "学习、新机会、务实",
      "reversed": "拖延、缺乏规划"
    },
    {
      "number": 76,
      "name": "钱币骑士",
      "type": "小阿卡纳",
      "suit": "钱币",
      "upright": "勤奋、可靠、责任感",
      "reversed": "懒散、停滞、任性"
    },
    {
      "number": 77,
      "name": "钱币王后",
      "type": "小阿卡纳",
      "suit": "钱币",
      "upright": "务实、母性、稳定",
      "reversed": "忽视家庭、物质焦虑"
    },
    {
      "number": 78,
      "name": "钱币国王",
      "type": "小阿卡纳",
      "suit": "钱币",
      "upright": "成功、财富、商业头脑",
      "reversed": "贪婪、挥霍、财务失策"
    }
  ],
  "spreads": {
    "single": {
      "name": "单牌指引",
      "description": "最简单的牌阵，一张牌直接回应你当前最需要关注的问题或能量指引，适合快速占卜和日常指引。",
      "cardCount": 1,
      "positions": [
        "当前指引"
      ],
      "defaultQuestions": [
        "今天我需要关注什么？",
        "我现在最需要的指引是什么？",
        "宇宙想要告诉我什么？",
        "我应该如何面对当前的困惑？",
        "今日的能量指引"
      ]
    },
    "three": {
      "name": "时间流牌阵",
      "description": "经典的三牌阵，从过去、现在、未来三个时间维度分析问题的发展脉络，了解因果联系与趋势。",
      "cardCount": 3,
      "positions": [
        "过去",
        "现在",
        "未来"
      ],
      "defaultQuestions": [
        "我的人生发展趋势如何？",
        "这个问题的来龙去脉是什么？",
        "我的过去如何影响现在和未来？",
        "我应该如何规划接下来的发展？",
        "时间会如何改变我的处境？"
      ]
    },
    "love": {
      "name": "爱情牌阵",
      "description": "专门为感情问题设计的五张牌阵，深入分析你和对方的内心世界，了解关系现状，获得发展建议，预见未来走向。",
      "cardCount": 5,
      "positions": [
        "你的内心",
        "对方的内心",
        "关系现状",
        "发展建议",
        "未来走向"
      ],
      "defaultQuestions": [
        "我和TA的感情会如何发展？",
        "TA对我的真实想法是什么？",
        "我们的关系现在处于什么状态？",
        "如何改善我们之间的关系？",
        "我的感情生活会有什么变化？",
        "我应该如何表达我的感情？",
        "这段关系值得我继续投入吗？"
      ]
    },
    "career": {
      "name": "事业牌阵",
      "description": "全面分析事业发展和职场问题，了解当前状况，发现自身优势，识别挑战，把握机会，获得行动建议。",
      "cardCount": 6,
      "positions": [
        "当前状况",
        "优势",
        "挑战",
        "机会",
        "行动建议",
        "结果"
      ],
      "defaultQuestions": [
        "我的事业发展前景如何？",
        "我应该换工作吗？",
        "如何在职场中获得更好的发展？",
        "我的职业规划应该如何调整？",
        "这个工作机会适合我吗？",
        "如何提升我的职场竞争力？",
        "我的事业瓶颈如何突破？"
      ]
    },
    "decision": {
      "name": "选择牌阵",
      "description": "面临重要决定时的最佳助手，分析现状，比较两个不同选择的走向与结果，获得最佳建议。",
      "cardCount": 6,
      "positions": [
        "现状",
        "选择A",
        "选择A结果",
        "选择B",
        "选择B结果",
        "最佳建议"
      ],
      "defaultQuestions": [
        "我应该选择A还是B？",
        "这两个选择哪个更适合我？",
        "我应该接受这个offer吗？",
        "搬家还是留在原地？",
        "继续这段关系还是分手？",
        "创业还是继续打工？",
        "出国还是留在国内发展？"
      ]
    },
    "celtic": {
      "name": "凯尔特十字",
      "description": "塔罗占卜中最经典和最全面的十张牌阵，适合深度分析复杂问题，从多个角度全面了解情况，获得深刻洞察。",
      "cardCount": 10,
      "positions": [
        "当前状况",
        "挑战/阻碍",
        "遥远过去",
        "近期过去",
        "可能未来",
        "近期未来",
        "你的态度",
        "外界影响",
        "内心恐惧",
        "最终结果"
      ],
      "defaultQuestions": [
        "我人生的整体状况如何？",
        "这个复杂问题的全面分析是什么？",
        "我的人生方向是否正确？",
        "如何解决我面临的复杂困境？",
        "我的人生会有什么重大转变？",
        "我的内心世界和外在环境如何平衡？"
      ]
    },
    "chakra": {
      "name": "七脉轮牌阵",
      "description": "基于古老的脉轮理论，分析身心灵各个层面的状态，帮助你了解能量流动，找到平衡点，实现整体和谐。",
      "cardCount": 7,
      "positions": [
        "海底轮(生存)",
        "脐轮(情感)",
        "太阳轮(意志)",
        "心轮(爱)",
        "喉轮(表达)",
        "眉心轮(直觉)",
        "顶轮(灵性)"
      ],
      "defaultQuestions": [
        "我的身心灵状态如何？",
        "如何平衡我的各个脉轮能量？",
        "我的能量阻塞在哪里？",
        "如何提升我的整体能量状态？",
        "我的灵性成长方向是什么？",
        "如何实现内在的和谐统一？"
      ]
    },
    "mindBodySpirit": {
      "name": "身心灵牌阵",
      "description": "检视个人在思想、情感和精神层面的状态，找到内在平衡与和谐。",
      "cardCount": 3,
      "positions": [
        "心灵/思想",
        "身体/行动",
        "精神/灵性"
      ],
      "defaultQuestions": [
        "我当前的身心灵状态如何？",
        "我需要在哪个层面进行调整？",
        "如何获得内在的平衡？",
        "我的思想、行动和灵性是否一致？"
      ]
    },
    "horseshoe": {
      "name": "马蹄铁牌阵",
      "description": "对特定问题提供一个全面的七牌概述，涵盖过去、现在、未来、建议和最终结果等七个方面。",
      "cardCount": 7,
      "positions": [
        "过去的影响",
        "现在的状况",
        "未来的发展",
        "给你的建议",
        "环境的影响",
        "你的希望与恐惧",
        "最终的结果"
      ],
      "defaultQuestions": [
        "关于这件事，我需要知道些什么？",
        "这个状况的全面分析是怎样的？",
        "我应该如何应对当前的挑战？",
        "这个决定的最终结果会是什么？"
      ]
    },
    "year": {
      "name": "年运牌阵",
      "description": "专为年度运势分析设计的综合牌阵，全面预测一整年的发展趋势，涵盖整体运势、季度、爱情、事业、财运和健康。",
      "cardCount": 12,
      "positions": [
        "整体运势",
        "1-3月",
        "4-6月",
        "7-9月",
        "10-12月",
        "爱情",
        "事业",
        "财运",
        "健康",
        "建议",
        "挑战",
        "机遇"
      ],
      "defaultQuestions": [
        "我今年的整体运势如何？",
        "新的一年我应该关注什么？",
        "今年我的爱情和事业会如何发展？",
        "今年我会遇到什么机遇和挑战？",
        "如何让今年过得更加顺利？",
        "今年我的财运状况如何？",
        "今年我需要特别注意什么？"
      ]
    },
    "loveProspect": {
      "name": "桃花/单身感情",
      "description": "专为单身人士设计的感情预测牌阵，了解自身吸引力、遇到桃花的可能性以及感情发展的方向。",
      "cardCount": 3,
      "positions": [
        "自身状态",
        "桃花机会",
        "发展建议"
      ],
      "defaultQuestions": [
        "我什么时候会遇到合适的对象？",
        "我的桃花运如何？",
        "我该如何提升自己的吸引力？",
        "我理想中的感情会在哪里出现？",
        "我现在准备好迎接新恋情了吗？"
      ]
    },
    "relationshipHeal": {
      "name": "人际关系修复",
      "description": "帮助分析和修复破裂或紧张的人际关系，了解问题根源、对方想法、修复可能性及行动建议。",
      "cardCount": 4,
      "positions": [
        "问题根源",
        "对方想法",
        "修复可能性",
        "行动建议"
      ],
      "defaultQuestions": [
        "我们之间的问题出在哪里？",
        "这段关系还能修复吗？",
        "对方现在是怎么想的？",
        "我应该主动道歉还是等待？",
        "如何才能重新建立信任？"
      ]
    },
    "workPlan": {
      "name": "工作计划",
      "description": "针对具体项目或工作计划的四牌阵，分析当前处境、资源与阻碍、最佳策略以及预期成果。",
      "cardCount": 4,
      "positions": [
        "当前处境",
        "资源与阻碍",
        "最佳策略",
        "预期成果"
      ],
      "defaultQuestions": [
        "这个项目的前景如何？",
        "我应该如何推进我的计划？",
        "有哪些潜在的风险需要注意？",
        "我具备完成这个项目所需的资源吗？",
        "这个计划的最终成果会怎样？"
      ]
    },
    "daily": {
      "name": "日运牌阵",
      "description": "每日三牌指引，帮助你了解当天的能量主题、需要注意的事项以及适合采取的行动，让每一天更有方向。",
      "cardCount": 3,
      "positions": [
        "今日能量",
        "注意事项",
        "行动建议"
      ],
      "defaultQuestions": [
        "今天我的能量状态如何？",
        "今天有什么我需要特别留意的事？",
        "今天最适合做什么？",
        "今天的运势如何影响我的计划？"
      ]
    },
    "finances": {
      "name": "财运牌阵",
      "description": "专门分析财务状况和财富运势的牌阵，了解当前的财务状态、潜在机会、风险以及理财建议。",
      "cardCount": 5,
      "positions": [
        "当前财务状况",
        "潜在机会",
        "潜在风险",
        "理财建议",
        "未来走向"
      ],
      "defaultQuestions": [
        "我近期的财运如何？",
        "我应该如何改善我的财务状况？",
        "这个投资机会值得把握吗？",
        "我该如何理财才能获得更好的收益？",
        "我的财务瓶颈如何突破？"
      ]
    }
  }
}